dash_addons/__init__.py
dash_addons/img_converter.py
dash_addons/utils.py
dash_addons-0.0.5.dist-info/LICENSE
dash_addons-0.0.5.dist-info/METADATA
dash_addons-0.0.5.dist-info/WHEEL
dash_addons-0.0.5.dist-info/top_level.txt
dash_addons-0.0.5.dist-info/RECORD
