Metadata-Version: 2.1
Name: dash-addons
Version: 0.0.5
Summary: Additional toolbox for Plotly Dash
Home-page: https://github.com/Janus-Shiau/dash_addons
Author: Jia-Yau Shiau
Author-email: jiayau.shiau@gmail.com
License: Apache Software License (Apache-2.0)
Requires-Python: >=3.7
License-File: LICENSE
Requires-Dist: dash
Requires-Dist: numpy
Requires-Dist: Pillow
